file_organizer_pro/__init__.py
file_organizer_pro/organizer.py
file_organizer_pro/utils.py
file_categorizer-0.1.3.dist-info/LICENSE.txt
file_categorizer-0.1.3.dist-info/METADATA
file_categorizer-0.1.3.dist-info/WHEEL
file_categorizer-0.1.3.dist-info/top_level.txt
file_categorizer-0.1.3.dist-info/RECORD
