Metadata-Version: 2.1
Name: file-categorizer
Version: 0.1.3
Summary: A Python package to organize files by type.
Home-page: https://github.com/Abhi00kh/file-categorizer
Author: Abhijit Khule
Author-email: abhijitkhule0@gmail.com
Classifier: Programming Language :: Python :: 3
Classifier: License :: OSI Approved :: MIT License
Classifier: Operating System :: OS Independent
Requires-Python: >=3.6
License-File: LICENSE.txt
